cobrawap/VERSION
cobrawap/__init__.py
cobrawap/__main__.py
cobrawap/cmd_utils.py
cobrawap/pipeline/README.rst
cobrawap/pipeline/Snakefile
cobrawap/pipeline/__init__.py
cobrawap/pipeline/environment.yaml
cobrawap/pipeline/report.rst
cobrawap/pipeline/settings_template.py
cobrawap/pipeline/configs/config_template.yaml
cobrawap/pipeline/stage01_data_entry/README.rst
cobrawap/pipeline/stage01_data_entry/Snakefile
cobrawap/pipeline/stage01_data_entry/report.rst
cobrawap/pipeline/stage01_data_entry/configs/config_template.yaml
cobrawap/pipeline/stage01_data_entry/scripts/__init__.py
cobrawap/pipeline/stage01_data_entry/scripts/check_input.py
cobrawap/pipeline/stage01_data_entry/scripts/enter_data_template.py
cobrawap/pipeline/stage01_data_entry/scripts/plot_traces.py
cobrawap/pipeline/stage02_processing/README.rst
cobrawap/pipeline/stage02_processing/Snakefile
cobrawap/pipeline/stage02_processing/report.rst
cobrawap/pipeline/stage02_processing/configs/config_template.yaml
cobrawap/pipeline/stage02_processing/scripts/__init__.py
cobrawap/pipeline/stage02_processing/scripts/background_subtraction.py
cobrawap/pipeline/stage02_processing/scripts/check_input.py
cobrawap/pipeline/stage02_processing/scripts/detrending.py
cobrawap/pipeline/stage02_processing/scripts/frequency_filter.py
cobrawap/pipeline/stage02_processing/scripts/logMUA_estimation.py
cobrawap/pipeline/stage02_processing/scripts/normalization.py
cobrawap/pipeline/stage02_processing/scripts/phase_transform.py
cobrawap/pipeline/stage02_processing/scripts/plot_power_spectrum.py
cobrawap/pipeline/stage02_processing/scripts/plot_processed_trace.py
cobrawap/pipeline/stage02_processing/scripts/roi_selection.py
cobrawap/pipeline/stage02_processing/scripts/spatial_downsampling.py
cobrawap/pipeline/stage02_processing/scripts/subsampling.py
cobrawap/pipeline/stage02_processing/scripts/zscore.py
cobrawap/pipeline/stage03_trigger_detection/README.rst
cobrawap/pipeline/stage03_trigger_detection/Snakefile
cobrawap-0.2.3.dist-info/entry_points.txt
cobrawap-0.2.3.dist-info/licenses/LICENSE
cobrawap-0.2.3.dist-info/WHEEL
cobrawap-0.2.3.dist-info/METADATA
cobrawap-0.2.3.dist-info/RECORD
