Metadata-Version: 2.4
Name: cobrawap
Version: 0.2.3
Summary: Collaborative Brain Wave Analysis Pipeline (Cobrawap)
Author-email: Cobrawap authors and contributors <contact@cobrawap.org>
Requires-Python: >=3.8
License-File: LICENSE
Requires-Dist: ruamel.yaml == 0.17.32
Requires-Dist: jinja2 >= 2.10.3
Requires-Dist: scipy >= 1.7.3
Requires-Dist: pygments >= 2.4.2
Requires-Dist: snakemake >= 7.10.0, < 8.0.0
Requires-Dist: h5py
Requires-Dist: shapely
Requires-Dist: elephant >= 1.0.0
Requires-Dist: neo >= 0.10.2
Requires-Dist: nixio >= 1.5.3
Requires-Dist: pillow >= 7.0.0
Requires-Dist: pandas >= 1.2.0
Requires-Dist: pulp < 2.8
Requires-Dist: scikit-learn >= 1.1.0
Requires-Dist: scikit-image >= 0.19.0
Requires-Dist: matplotlib >= 3.5.1
Requires-Dist: seaborn
Requires-Dist: networkx
Requires-Dist: black ; extra == "dev"
Requires-Dist: bump2version ; extra == "dev"
Requires-Dist: flake8 ; extra == "dev"
Requires-Dist: mypy ; extra == "dev"
Requires-Dist: pre-commit ; extra == "dev"
Requires-Dist: pydocstyle ; extra == "dev"
Requires-Dist: pylint ; extra == "dev"
Requires-Dist: pytest ; extra == "dev"
Requires-Dist: pytest-black ; extra == "dev"
Requires-Dist: pytest-cov ; extra == "dev"
Requires-Dist: pytest-flake8 ; extra == "dev"
Requires-Dist: pytest-mypy ; extra == "dev"
Requires-Dist: pytest-pydocstyle ; extra == "dev"
Requires-Dist: pytest-pylint ; extra == "dev"
Requires-Dist: pytest-xdist ; extra == "dev"
Requires-Dist: sphinx>=3.3.0 ; extra == "doc"
Requires-Dist: numpydoc>=1.1.0 ; extra == "doc"
Requires-Dist: sphinx-tabs>=1.3.0 ; extra == "doc"
Requires-Dist: sphinx-argparse>=0.4.0 ; extra == "doc"
Requires-Dist: sphinx-autodoc-typehints ; extra == "doc"
Requires-Dist: pygments ; extra == "doc"
Requires-Dist: recommonmark ; extra == "doc"
Project-URL: Bug Tracker, https://github.com/NeuralEnsemble/cobrawap/issues
Project-URL: Homepage, https://cobrawap.readthedocs.io/
Provides-Extra: cwl
Provides-Extra: dev
Provides-Extra: doc
